pykrakenfiles/__init__.py
pykrakenfiles/cli.py
pykrakenfiles/main.py
pykrakenfiles-0.0.2.dist-info/LICENSE
pykrakenfiles-0.0.2.dist-info/METADATA
pykrakenfiles-0.0.2.dist-info/WHEEL
pykrakenfiles-0.0.2.dist-info/entry_points.txt
pykrakenfiles-0.0.2.dist-info/top_level.txt
pykrakenfiles-0.0.2.dist-info/RECORD
