Metadata-Version: 2.1
Name: pykrakenfiles
Version: 0.0.2
Summary: Krakenfiles upload API wrapper
Home-page: https://github.com/bontoutou00/pykrakenfiles
Author: bontoutou
Project-URL: Bug Tracker, https://github.com/bontoutou00/pykrakenfiles/issues
Keywords: krakenfiles,upload
Classifier: Programming Language :: Python :: 3
Classifier: License :: OSI Approved :: MIT License
Classifier: Operating System :: OS Independent
Requires-Python: >=3.7
License-File: LICENSE
Requires-Dist: requests
Requires-Dist: tqdm
Requires-Dist: requests-toolbelt
Requires-Dist: pyyAML
